{
    "page": 1,
    "results": [
        {
            "adult": false,
            "backdrop_path": "/2meX1nMdScFOoV4370rqHWKmXhY.jpg",
            "genre_ids": [10759, 9648, 18],
            "id": 93405,
            "origin_country": ["KR"],
            "original_language": "ko",
            "original_name": "오징어 게임",
            "overview": "Hundreds of cash-strapped players accept a strange invitation to compete in children's games. Inside, a tempting prize awaits — with deadly high stakes.",
            "popularity": 13121.205,
            "poster_path": "/dDlEmu3EZ0Pgg93K2SVNLCjCSvE.jpg",
            "first_air_date": "2021-09-17",
            "name": "Squid Game",
            "vote_average": 7.8,
            "vote_count": 14636
        },
        {
            "adult": false,
            "backdrop_path": "/fRzSn59mtc4BV3cckdHntRKaufM.jpg",
            "genre_ids": [35, 18, 10751],
            "id": 84791,
            "origin_country": ["HK"],
            "original_language": "cn",
            "original_name": "愛·回家",
            "overview": "MA FU, a retired employee of the HK Correctional Services Department, moved back to live with his son after retirement. MA FU treats and disciplines everyone in his family as if they were the offenders he works with in his job. His youngest son MA CHONG feels like he's in jail when he gets home, and his father is even often involved with his job as a paralegal. The father and son get into disputes daily and his elder brother MA KEUNG and his wife LO LAI SEUNG are often stuck in between and have to settle the disputes. The couple also holds the heavy responsibility of raising their kids. Three generations in the MA family all live together and encounter different situations, experiences and system of values.",
            "popularity": 3270.112,
            "poster_path": "/nQwKCmgbpjb3wIf816t4WNgxzcR.jpg",
            "first_air_date": "2012-05-14",
            "name": "Come Home Love",
            "vote_average": 8,
            "vote_count": 1
        },
        {
            "adult": false,
            "backdrop_path": "/n85GMdNw2pDVtkgoTdpHNpM89Uh.jpg",
            "genre_ids": [18],
            "id": 42316,
            "origin_country": ["IO"],
            "original_language": "hi",
            "original_name": "देवों के देव...महादेव",
            "overview": "He is the supreme being and the destroyer of evil. Witness lord Shiva's story, his avatars, and a union that sha more.",
            "popularity": 2615.504,
            "poster_path": "/oMzXcYsUVIt6pQEODc6FRe8IBug.jpg",
            "first_air_date": "2011-12-18",
            "name": "Devon Ke Dev...Mahadev",
            "vote_average": 9.1,
            "vote_count": 7
        },
        {
            "adult": false,
            "backdrop_path": "/mu3lEhGovyhKHPJzb7HNYtZUCDT.jpg",
            "genre_ids": [10766],
            "id": 206559,
            "origin_country": ["ZA"],
            "original_language": "af",
            "original_name": "Binnelanders",
            "overview": "A South African Afrikaans soap opera. It is set in and around the fictional private hospital, Binneland Kliniek, in Pretoria, and the storyline follows the trials, trauma and tribulations of the staff and patients of the hospital.",
            "popularity": 2235.035,
            "poster_path": "/3bzECfllho8PphdYujLUIuhncJD.jpg",
            "first_air_date": "2005-10-13",
            "name": "Binnelanders",
            "vote_average": 5.619,
            "vote_count": 80
        },
        {
            "adult": false,
            "backdrop_path": "/mFy2U5HVQ81hewd68897llwkwlc.jpg",
            "genre_ids": [16, 10759, 10765],
            "id": 60572,
            "origin_country": ["JP"],
            "original_language": "ja",
            "original_name": "ポケットモンスター",
            "overview": "Join Ash accompanied by his partner Pikachu, as he travels through many regions, meets new friends and faces new challenges on his quest to become a Pokémon Master.",
            "popularity": 2049.1,
            "poster_path": "/rOuGm07PxBhEsK9TaGPRQVJQm1X.jpg",
            "first_air_date": "1997-04-01",
            "name": "Pokémon",
            "vote_average": 7.8,
            "vote_count": 1814
        },
        {
            "adult": false,
            "backdrop_path": "/fQsIJQxE1D0Y0NpWSKwo489y5px.jpg",
            "genre_ids": [10764],
            "id": 204082,
            "origin_country": ["GB"],
            "original_language": "en",
            "original_name": "Squid Game: The Challenge",
            "overview": "In this reality competition show inspired by \"Squid Game,\" 456 players put their skills to the ultimate test for a life-changing $4.56 million prize.",
            "popularity": 1988.888,
            "poster_path": "/y85L9DWoaM2MYNg1p8QRywxXJsa.jpg",
            "first_air_date": "2023-11-22",
            "name": "Squid Game: The Challenge",
            "vote_average": 6.494,
            "vote_count": 359
        },
        {
            "adult": false,
            "backdrop_path": "/sztoil0XfQ0cSHy4PXmYW6uAdfQ.jpg",
            "genre_ids": [10764],
            "id": 65282,
            "origin_country": ["KR", "US"],
            "original_language": "ko",
            "original_name": "나 혼자 산다",
            "overview": "It can be a badge of honor to be “single.” “I Live Alone” is a documentary-style South Korean reality series that follows the members of a self-formed club called Rainbow, which is comprised of  celebrities who are single and live alone.",
            "popularity": 1982.208,
            "poster_path": "/1hqGagr94soBq70Lq7tPHvNmmxy.jpg",
            "first_air_date": "2013-03-22",
            "name": "Home Alone",
            "vote_average": 6.8,
            "vote_count": 16
        },
        {
            "adult": false,
            "backdrop_path": "/sgE2evtpaP5b9tavrgYCy2nKYLT.jpg",
            "genre_ids": [10764],
            "id": 52910,
            "origin_country": ["KR"],
            "original_language": "ko",
            "original_name": "정글의 법칙",
            "overview": "Law of the Jungle is a hybrid reality show combining elements of drama and documentary. The show is hosted by comedian Kim Byung Man, and each episode invites various celebrities from the various field. So far, many of idol stars and famous actors have appeared on the show. The show introduces viewers to exotic locations around the world where celebrities must work together in order to complete missions and survive. The cast celebrities travel to less habituated, natural places to survive on their own and experience life with local tribes and people. In each location, the guests are tasked to hunt and prepare their meals and also create shelter for the tribe. They sometimes confronted by many difficult challenges. Where will the tribe visit? And how will they survive on their own? Stay tuned to check out!",
            "popularity": 1759.368,
            "poster_path": "/b38QkTpxOiQM3Ex9NTc6jg9JAmw.jpg",
            "first_air_date": "2011-10-21",
            "name": "Law of the Jungle",
            "vote_average": 4.7,
            "vote_count": 7
        },
        {
            "adult": false,
            "backdrop_path": "/5APjn4LnV5wWk5DXq7ZewT6zzP1.jpg",
            "genre_ids": [10766],
            "id": 291,
            "origin_country": ["MY", "GB"],
            "original_language": "en",
            "original_name": "Coronation Street",
            "overview": "The residents of Coronation Street are ordinary, working-class people, and the show follows them through regular social and family interactions at home, in the workplace, and in their local pub, the Rovers Return Inn. Britain's longest-running soap.",
            "popularity": 1736.545,
            "poster_path": "/5x1HXqYqPyYw7oc7Isu1lvVmwRP.jpg",
            "first_air_date": "1960-12-09",
            "name": "Coronation Street",
            "vote_average": 5.3,
            "vote_count": 109
        },
        {
            "adult": false,
            "backdrop_path": "/4uWvmON2pqDJtpPAsHMggdDFFrn.jpg",
            "genre_ids": [80, 18],
            "id": 549,
            "origin_country": ["US"],
            "original_language": "en",
            "original_name": "Law & Order",
            "overview": "In cases ripped from the headlines, police investigate serious and often deadly crimes, weighing the evidence and questioning the suspects until someone is taken into custody. The district attorney's office then builds a case to convict the perpetrator by proving the person guilty beyond a reasonable doubt. Working together, these expert teams navigate all sides of the complex criminal justice system to make New York a safer place.",
            "popularity": 1640.258,
            "poster_path": "/6vFL8S6Cci8s7SHWXz60xOisGBC.jpg",
            "first_air_date": "1990-09-13",
            "name": "Law & Order",
            "vote_average": 7.4,
            "vote_count": 583
        },
        {
            "adult": false,
            "backdrop_path": "/9rdlZYoFcoSG7pVSxJ7XbzWxcDo.jpg",
            "genre_ids": [35, 10759, 16, 10765],
            "id": 57706,
            "origin_country": ["JP"],
            "original_language": "ja",
            "original_name": "らんま1/2",
            "overview": "Ranma Saotome, a teenage martial artist, and his father Genma travel to the 'cursed training ground' of Jusenkyo in China. There, despite the warnings of the Chinese guard, they fall into the cursed springs. From now on, whenever Ranma is doused in cold water, he turns into a girl and a cute, well-built redhead at that. Hot water changes him back into a man again, but only until the next time. To make matters worse, his father engages him to Akane Tendo, a girl who hates boys.",
            "popularity": 1553.785,
            "poster_path": "/qb1R5iLZcjIgdDIfXFQXmJadQPI.jpg",
            "first_air_date": "1989-04-15",
            "name": "Ranma ½",
            "vote_average": 8.6,
            "vote_count": 1399
        },
        {
            "adult": false,
            "backdrop_path": "/j5CR0gFPjwgmAXkV9HGaF4VMjIW.jpg",
            "genre_ids": [10766, 18, 35],
            "id": 257064,
            "origin_country": ["BR"],
            "original_language": "pt",
            "original_name": "Volta por Cima",
            "overview": "",
            "popularity": 1534.793,
            "poster_path": "/nyN8R0P1Hqwq7ksJz4O2BIAUd4W.jpg",
            "first_air_date": "2024-09-30",
            "name": "Volta por Cima",
            "vote_average": 6.4,
            "vote_count": 9
        },
        {
            "adult": false,
            "backdrop_path": "/mIKv5ABEKVajXvfxms9SGKxNpRW.jpg",
            "genre_ids": [35],
            "id": 46078,
            "origin_country": ["RU"],
            "original_language": "ru",
            "original_name": "Воронины",
            "overview": "The main characters of the series are an ordinary family. The family consists of the following: Kostya (a sports journalist), his wife Vera (a housewife) and their children: Masha and the twins Philip and Kirill. Right on the same landing, where the apartment of the young Voronin family is located, Kostya’s parents live: Galina Ivanovna (housewife, Kostya and Lyonya’s mother, Vera’s mother-in-law), Nikolai Petrovich (Kostya’s and Lyonya’s father, Vera’s father-in-law) and Lyonya (the major of the police) - Kostya's older brother.",
            "popularity": 1530.192,
            "poster_path": "/lKW2c9KrIhKy272AYZCzY2SSVcM.jpg",
            "first_air_date": "2009-11-16",
            "name": "The Voronins",
            "vote_average": 6.8,
            "vote_count": 41
        },
        {
            "adult": false,
            "backdrop_path": "/2wNuLc0cEoPz6PZItftrZLHjG2k.jpg",
            "genre_ids": [18, 10751],
            "id": 251691,
            "origin_country": ["SA"],
            "original_language": "ar",
            "original_name": "خريف القلب",
            "overview": "A devastating car accident unearths a long-buried secret that turns wealthy businessman Rashid and hardworking Nahla's life around; fifteen years ago, their daughters were switched at birth.",
            "popularity": 1522.286,
            "poster_path": "/8uDmIxjBx90y5OCwJDBADtQzxb7.jpg",
            "first_air_date": "2024-10-27",
            "name": "Autumn of the Heart",
            "vote_average": 4,
            "vote_count": 8
        },
        {
            "adult": false,
            "backdrop_path": "/tPLUHT2cQYJi66aSZZ1qrcu74Zq.jpg",
            "genre_ids": [10766, 18],
            "id": 257048,
            "origin_country": ["BR"],
            "original_language": "pt",
            "original_name": "Garota do Momento",
            "overview": "",
            "popularity": 1517.348,
            "poster_path": "/jFSkjQSZ5Td52igalpoTQRuHtk.jpg",
            "first_air_date": "2024-11-04",
            "name": "Garota do Momento",
            "vote_average": 7.9,
            "vote_count": 8
        },
        {
            "adult": false,
            "backdrop_path": "/4P2gbaCGdZyP4i95TmmA6nS9HJh.jpg",
            "genre_ids": [10764],
            "id": 64356,
            "origin_country": ["KR"],
            "original_language": "ko",
            "original_name": "슈퍼맨이 돌아왔다",
            "overview": "An up-close look at celebrity dads who have to take care of their kids for the next 48 hours without any help. Will it be a dad-tastrophe, or can they finish their wives' to-do lists while having fun with their kids?",
            "popularity": 1491.398,
            "poster_path": "/qjBx2RCnyyBPgu9qBV7j3UiXjeo.jpg",
            "first_air_date": "2013-11-03",
            "name": "The Return of Superman",
            "vote_average": 7.9,
            "vote_count": 12
        },
        {
            "adult": false,
            "backdrop_path": "/2w8FaLwwJTWr6ExUMeVgT2Th5YT.jpg",
            "genre_ids": [16, 35, 18, 10759],
            "id": 42705,
            "origin_country": ["JP"],
            "original_language": "ja",
            "original_name": "はじめの一歩",
            "overview": "Makunouchi Ippo is an ordinary high school student in Japan. Since he spends most of his time away from school helping his mother run the family business, he doesn't get to enjoy his younger years like most teenagers. Always a target for bullying at school (the family fishing business grants him a distinct odor), Ippo's life is one of hardship. One of these after-school bullying sessions turns Ippo's life around for the better, as he is saved by a boxer named Takamura. He decides to follow in Takamura's footsteps and train to become a boxer, giving his life direction and purpose. Ippo's path to perfecting his pugilistic prowess is just beginning...",
            "popularity": 1363.754,
            "poster_path": "/qC4taY6yB9BWJ8IxcbnXR8yUS4o.jpg",
            "first_air_date": "2000-10-03",
            "name": "Fighting Spirit",
            "vote_average": 8.7,
            "vote_count": 1086
        },
        {
            "adult": false,
            "backdrop_path": "/9zIqN0oMmaeFvBlccgw80sWed7I.jpg",
            "genre_ids": [10763, 35],
            "id": 13008,
            "origin_country": ["US"],
            "original_language": "en",
            "original_name": "TMZ",
            "overview": "Based on the popular gossip website, this entertainment newsmagazine delivers daily updates on Hollywood's rich, beautiful and screwed-up. The program often shows highlights of the day's staff meeting during which reporters pitch ideas for stories to air that day.",
            "popularity": 1360.641,
            "poster_path": "/ifFpUG51DJaQxwnZ35VwoGRFGGv.jpg",
            "first_air_date": "2007-09-10",
            "name": "TMZ",
            "vote_average": 4.813,
            "vote_count": 16
        },
        {
            "adult": false,
            "backdrop_path": "/lUrtMjiunomHPDC2sQNIxswbmdU.jpg",
            "genre_ids": [18, 80],
            "id": 3034,
            "origin_country": ["AT", "DE", "CH"],
            "original_language": "de",
            "original_name": "Tatort",
            "overview": "Tatort is a long-running German/Austrian/Swiss, crime television series set in various parts of these countries. The show is broadcast on the channels of ARD in Germany, ORF in Austria and SF1 in Switzerland.",
            "popularity": 1330.885,
            "poster_path": "/b6kIWHHifuc8qH0IpzVzUeXBnvq.jpg",
            "first_air_date": "1970-11-29",
            "name": "Scene of the Crime",
            "vote_average": 6.1,
            "vote_count": 109
        },
        {
            "adult": false,
            "backdrop_path": "/6wAu4kZiKov5WkavL7H2ZfwbGAo.jpg",
            "genre_ids": [10766, 18, 9648],
            "id": 237478,
            "origin_country": ["BR"],
            "original_language": "pt",
            "original_name": "Mania de Você",
            "overview": "The story begins with the ambiguous relationship between friends Viola and Luma, who seem predestined to literally enter each other's lives. Born on the same day, in very different situations, they meet years later, united by coincidences that go beyond their birthday. From humble origins, Viola moves with her boyfriend Mavi to Angra dos Reis, where Luma lives a luxurious life and dates Rudá, who ends up meeting Viola by chance. Thus begins the duo's journey, which goes from a passion for recipes to an obsession with the same man, from the immediate connection to the point of starting to live their friend’s reality, 10 years later. A journey divided between complicity and rivalry, which includes them in a love quadrangle and is impacted by a series of circumstances, twists and surprises, such as the secret surrounding a murder.",
            "popularity": 1312.357,
            "poster_path": "/cRMofv8YC4F1WnpF7cIqMpwSnwh.jpg",
            "first_air_date": "2024-09-09",
            "name": "Crazy About You",
            "vote_average": 5.111,
            "vote_count": 8
        }
    ],
    "total_pages": 9447,
    "total_results": 188925
}
